AUTHORS
LICENSE
MANIFEST.in
README.rst
setup.py
pyjswidgets/__init__.py
pyjswidgets/__pyjamas__.py
pyjswidgets/dynamic.py
pyjswidgets/dynamicajax.js
pyjswidgets/pygwt.browser.py
pyjswidgets/pygwt.py
pyjswidgets/pyjslib.PyJS.py
pyjswidgets/pyjslib.PyV8.py
pyjswidgets/pyjslib.pysm.py
pyjswidgets/pyjamas/Canvas2D.browser.py
pyjswidgets/pyjamas/Canvas2D.py
pyjswidgets/pyjamas/Cookies.browser.py
pyjswidgets/pyjamas/Cookies.py
pyjswidgets/pyjamas/DOM.browser.py
pyjswidgets/pyjamas/DOM.ie6.py
pyjswidgets/pyjamas/DOM.mozilla.py
pyjswidgets/pyjamas/DOM.mshtml.py
pyjswidgets/pyjamas/DOM.oldmoz.py
pyjswidgets/pyjamas/DOM.opera.py
pyjswidgets/pyjamas/DOM.py
pyjswidgets/pyjamas/DOM.pyqt4.py
pyjswidgets/pyjamas/DOM.pyv8.py
pyjswidgets/pyjamas/DOM.pywebkitdfb.py
pyjswidgets/pyjamas/DOM.pywebkitgtk.py
pyjswidgets/pyjamas/DOM.safari.py
pyjswidgets/pyjamas/DeferredCommand.py
pyjswidgets/pyjamas/EventController.py
pyjswidgets/pyjamas/Factory.py
pyjswidgets/pyjamas/HTTPRequest.browser.py
pyjswidgets/pyjamas/HTTPRequest.ie6.py
pyjswidgets/pyjamas/HTTPRequest.py
pyjswidgets/pyjamas/History.browser.py
pyjswidgets/pyjamas/History.ie6.py
pyjswidgets/pyjamas/History.py
pyjswidgets/pyjamas/History.safari.py
pyjswidgets/pyjamas/JSONService.browser.py
pyjswidgets/pyjamas/JSONService.py
pyjswidgets/pyjamas/JSONTranslations.py
pyjswidgets/pyjamas/Location.browser.py
pyjswidgets/pyjamas/Location.ie6.py
pyjswidgets/pyjamas/Location.opera.py
pyjswidgets/pyjamas/Location.py
pyjswidgets/pyjamas/PyExternalMod.py
pyjswidgets/pyjamas/Timer.browser.py
pyjswidgets/pyjamas/Timer.mshtml.py
pyjswidgets/pyjamas/Timer.py
pyjswidgets/pyjamas/Timer.pywebkitdfb.py
pyjswidgets/pyjamas/Timer.pywebkitgtk.py
pyjswidgets/pyjamas/Window.browser.py
pyjswidgets/pyjamas/Window.ie6.py
pyjswidgets/pyjamas/Window.mshtml.py
pyjswidgets/pyjamas/Window.py
pyjswidgets/pyjamas/Window.pywebkitdfb.py
pyjswidgets/pyjamas/Window.pywebkitgtk.py
pyjswidgets/pyjamas/Window.safari.py
pyjswidgets/pyjamas/XMLDoc.browser.py
pyjx_gwt.egg-info/PKG-INFO
pyjx_gwt.egg-info/SOURCES.txt
pyjx_gwt.egg-info/dependency_links.txt
pyjx_gwt.egg-info/not-zip-safe
pyjx_gwt.egg-info/requires.txt
pyjx_gwt.egg-info/top_level.txt